setup.py
sphinx_serve/__init__.py
sphinx_serve/__main__.py
sphinx_serve/sphinx_serve.py
sphinx_serve.egg-info/PKG-INFO
sphinx_serve.egg-info/SOURCES.txt
sphinx_serve.egg-info/dependency_links.txt
sphinx_serve.egg-info/entry_points.txt
sphinx_serve.egg-info/top_level.txt