Metadata-Version: 1.1
Name: sphinx-serve
Version: 1.0.1
Summary: Preview sphinx documentation locally
Home-page: https://github.com/tlatsas/sphinx-serve
Author: Tasos Latsas
Author-email: tlatsas@gmx.com
License: MIT
Platform: UNKNOWN
Classifier: Development Status :: 5 - Production/Stable
Classifier: Environment :: Console
Classifier: Programming Language :: Python
Classifier: Programming Language :: Python :: 2.7
Classifier: Programming Language :: Python :: 3
Classifier: Topic :: Utilities
Classifier: Topic :: Documentation
Classifier: Intended Audience :: Developers
Classifier: License :: OSI Approved :: MIT License
